{
  "version": "2.0",
  "timestamp": "2026-01-21T19:01:21.380Z",
  "layers": [
    {
      "id": "layer-1",
      "activeElements": [
        "rings",
        "fbm-noise",
        "vector-field"
      ],
      "elementOrder": [
        "vector-field",
        "fbm-noise",
        "rings",
        "fbm-value-noise",
        "fractal",
        "sphere-raymarch",
        "voronoi-noise",
        "polar-coordinates",
        "wave-patterns",
        "glow-bloom",
        "twist-distortion",
        "kaleidoscope",
        "turbulence",
        "gradient-mask",
        "hexagonal-grid",
        "simplex-noise",
        "particle-system",
        "plane-grid",
        "box-torus-sdf",
        "edge-detection",
        "blur",
        "normal-mapping",
        "lighting-shading",
        "blending-modes",
        "chromatic-aberration",
        "color-grading",
        "block-displacement",
        "block-edge-brightness",
        "block-color-glitch",
        "scanlines",
        "rgb-separation"
      ],
      "parameters": {
        "fbm-noise.fbmScale": 2.6,
        "fbm-noise.fbmOctaves": 8,
        "fbm-noise.fbmLacunarity": 1.5,
        "fbm-noise.fbmGain": 0.7,
        "fbm-noise.fbmTimeSpeed": 1.8,
        "rings.ringCenterX": 1,
        "rings.ringCenterY": -0.2,
        "rings.ringRadius": 0.1,
        "rings.ringFrequency": 4,
        "rings.ringAmplitude": 0.4,
        "vector-field.vfFrequencyX": 2,
        "vector-field.vfFrequencyY": 0.9,
        "vector-field.vfFrequencyZ": 3.2,
        "vector-field.vfAmplitude": 3.8,
        "vector-field.vfRadialStrength": 2.8,
        "vector-field.vfHarmonicAmplitude": 2.4,
        "sphere-raymarch.sphereRadius": 1,
        "sphere-raymarch.sphereGlowIntensity": 0.5,
        "sphere-raymarch.raymarchSteps": 40,
        "fractal.fractalIntensity": 1.5,
        "fractal.fractalLayers": 1.5,
        "fractal.fractalIterations": 4,
        "fbm-value-noise.fbmValueScale": 1.9,
        "fbm-value-noise.fbmValueOctaves": 3,
        "fbm-value-noise.fbmValueLacunarity": 2.05,
        "fbm-value-noise.fbmValueGain": 0.55,
        "fbm-value-noise.fbmValueTimeSpeed": 2.7,
        "rings.ringIntensity": 1.56,
        "rings.ringTimeOffset": 0,
        "fbm-noise.fbmIntensity": 0.5,
        "fbm-noise.fbmTimeOffset": 0,
        "vector-field.vfAmplitudeX": 1,
        "vector-field.vfAmplitudeY": 1,
        "vector-field.vfAmplitudeZ": 1,
        "vector-field.vfRadialCenterX": 0,
        "vector-field.vfRadialCenterY": 0,
        "vector-field.vfTimeOffset": 0
      },
      "blendingMode": 0,
      "opacity": 1,
      "visible": true,
      "colorConfig": {
        "mode": "thresholds",
        "transitionWidth": 0.18,
        "ditherStrength": 0.5,
        "pixelSize": 1,
        "startColor": {
          "l": 0.24751650459977886,
          "c": 0.048576064541023735,
          "h": 160.42424176639113
        },
        "endColor": {
          "l": 0.4982658439623441,
          "c": 0.23131861740993134,
          "h": 279.07281814419184
        },
        "stops": 6,
        "lCurve": {
          "x1": 0,
          "y1": 0,
          "x2": 1,
          "y2": 1
        },
        "cCurve": {
          "x1": 0,
          "y1": 0,
          "x2": 1,
          "y2": 1
        },
        "hCurve": {
          "x1": 0,
          "y1": 0,
          "x2": 1,
          "y2": 1
        },
        "toneMapping": {
          "exposure": 1,
          "contrast": 1,
          "saturation": 1
        }
      }
    },
    {
      "id": "layer-2",
      "activeElements": [],
      "elementOrder": [
        "fbm-noise",
        "fbm-value-noise",
        "rings",
        "vector-field",
        "sphere-raymarch",
        "fractal",
        "voronoi-noise",
        "polar-coordinates",
        "wave-patterns",
        "glow-bloom",
        "twist-distortion",
        "kaleidoscope",
        "turbulence",
        "gradient-mask",
        "hexagonal-grid",
        "simplex-noise",
        "particle-system",
        "plane-grid",
        "box-torus-sdf",
        "edge-detection",
        "blur",
        "normal-mapping",
        "lighting-shading",
        "blending-modes",
        "chromatic-aberration",
        "color-grading",
        "block-displacement",
        "block-edge-brightness",
        "block-color-glitch",
        "scanlines",
        "rgb-separation"
      ],
      "parameters": {},
      "blendingMode": 0,
      "opacity": 1,
      "visible": false,
      "colorConfig": {
        "mode": "thresholds",
        "transitionWidth": 0.005,
        "ditherStrength": 0,
        "pixelSize": 1,
        "startColor": {
          "l": 0.24751650459977886,
          "c": 0.048576064541023735,
          "h": 160.42424176639113
        },
        "endColor": {
          "l": 0.42453928748013964,
          "c": 0.19315528843747376,
          "h": 279.44050217215556
        },
        "stops": 6,
        "lCurve": {
          "x1": 0,
          "y1": 0,
          "x2": 1,
          "y2": 1
        },
        "cCurve": {
          "x1": 0,
          "y1": 0,
          "x2": 1,
          "y2": 1
        },
        "hCurve": {
          "x1": 0,
          "y1": 0,
          "x2": 1,
          "y2": 1
        },
        "toneMapping": {
          "exposure": 1,
          "contrast": 1,
          "saturation": 1
        }
      }
    }
  ],
  "fxLayer": {
    "id": "fx",
    "activeElements": [],
    "elementOrder": [
      "glow-bloom",
      "gradient-mask",
      "edge-detection",
      "blur",
      "normal-mapping",
      "lighting-shading",
      "blending-modes",
      "chromatic-aberration",
      "color-grading",
      "block-edge-brightness",
      "block-color-glitch",
      "scanlines",
      "rgb-separation"
    ],
    "parameters": {}
  },
  "colorConfig": {
    "mode": "thresholds",
    "transitionWidth": 0.18,
    "ditherStrength": 0.5,
    "pixelSize": 1,
    "startColor": {
      "l": 0.24751650459977886,
      "c": 0.048576064541023735,
      "h": 160.42424176639113
    },
    "endColor": {
      "l": 0.4982658439623441,
      "c": 0.23131861740993134,
      "h": 279.07281814419184
    },
    "stops": 6,
    "lCurve": {
      "x1": 0,
      "y1": 0,
      "x2": 1,
      "y2": 1
    },
    "cCurve": {
      "x1": 0,
      "y1": 0,
      "x2": 1,
      "y2": 1
    },
    "hCurve": {
      "x1": 0,
      "y1": 0,
      "x2": 1,
      "y2": 1
    },
    "toneMapping": {
      "exposure": 1,
      "contrast": 1,
      "saturation": 1
    }
  },
  "timelineConfig": {
    "value": 22.22,
    "min": 0,
    "max": 100,
    "step": 0.01
  },
  "exportConfig": {
    "resolution": [
      1600,
      1200
    ],
    "format": "png",
    "quality": 1
  }
}